README.md
setup.py
wmonitor/__init__.py
wmonitor/constant.py
wmonitor/demo.py
wmonitor/metric.py
wmonitor.egg-info/PKG-INFO
wmonitor.egg-info/SOURCES.txt
wmonitor.egg-info/dependency_links.txt
wmonitor.egg-info/top_level.txt