Metadata-Version: 2.1
Name: wmonitor
Version: 0.0.9
Summary: send http request to wmonitor
Home-page: UNKNOWN
Author: chunyu.piao
Author-email: chunyu.piao@bianlifeng.com
License: UNKNOWN
Platform: UNKNOWN
Classifier: Programming Language :: Python :: 3
Classifier: License :: OSI Approved :: MIT License
Classifier: Operating System :: OS Independent
